memora/__init__.py
memora/cli.py
memora/tuner.py
memora/utils.py
memora_ai-0.1.0.dist-info/METADATA
memora_ai-0.1.0.dist-info/WHEEL
memora_ai-0.1.0.dist-info/entry_points.txt
memora_ai-0.1.0.dist-info/top_level.txt
memora_ai-0.1.0.dist-info/RECORD
