Metadata-Version: 2.4
Name: memora-ai
Version: 0.1.0
Summary: Train Smarter, Not Harder!
Requires-Python: >=3.8
